x11_automation/__init__.py
x11_automation/__main__.py
x11_automation/get_win_geometry.py
x11_automation/move_mouse_to_new_window.py
x11_automation/send.py
x11_automation/win_activate.py
x11_automation/win_exists.py
x11_automation/win_get_process.py
x11_automation/win_wait_active.py
x11_automation/x11_automation.py
x11_automation-0.3.6.dist-info/.gitignore
x11_automation-0.3.6.dist-info/LICENSE.txt
x11_automation-0.3.6.dist-info/METADATA
x11_automation-0.3.6.dist-info/WHEEL
x11_automation-0.3.6.dist-info/top_level.txt
x11_automation-0.3.6.dist-info/RECORD
