Metadata-Version: 2.1
Name: x11-automation
Version: 0.3.6
Summary: X11-Automation
Home-page: 
Author: Dmitry Yakovlev
Author-email: opensuse12@gmail.com
Requires-Python: >=3.6
License-File: LICENSE.txt
Requires-Dist: ewmh
Requires-Dist: opencv-python
Requires-Dist: numpy
Requires-Dist: mouse
